mgo_processor/__init__.py
mgo_processor/controllers/__init__.py
mgo_processor/controllers/decline_manager.cpython-310-x86_64-linux-gnu.so
mgo_processor/controllers/gh.cpython-310-x86_64-linux-gnu.so
mgo_processor/controllers/ml/__init__.py
mgo_processor/controllers/ml/picker.cpython-310-x86_64-linux-gnu.so
mgo_processor/controllers/ml/sample_rule.cpython-310-x86_64-linux-gnu.so
mgo_processor/controllers/processor/__init__.py
mgo_processor/controllers/processor/bill_methods.cpython-310-x86_64-linux-gnu.so
mgo_processor/controllers/processor/custom_shipper.cpython-310-x86_64-linux-gnu.so
mgo_processor/controllers/processor/entry_points.cpython-310-x86_64-linux-gnu.so
mgo_processor/controllers/processor/gc_exec.cpython-310-x86_64-linux-gnu.so
mgo_processor/controllers/processor/load_balancer.cpython-310-x86_64-linux-gnu.so
mgo_processor/controllers/processor/order_methods.cpython-310-x86_64-linux-gnu.so
mgo_processor/controllers/processor/rehasher.cpython-310-x86_64-linux-gnu.so
mgo_processor/controllers/processor/timer.cpython-310-x86_64-linux-gnu.so
mgo_processor/controllers/processor/tp_gateways.cpython-310-x86_64-linux-gnu.so
mgo_processor/controllers/processor/ll_processor/__init__.py
mgo_processor/controllers/processor/ll_processor/base.cpython-310-x86_64-linux-gnu.so
mgo_processor/controllers/processor/ll_processor/confirmations.cpython-310-x86_64-linux-gnu.so
mgo_processor/controllers/processor/ll_processor/dct.cpython-310-x86_64-linux-gnu.so
mgo_processor/controllers/processor/ll_processor/entry_points.cpython-310-x86_64-linux-gnu.so
mgo_processor/controllers/processor/ll_processor/initial_ds.cpython-310-x86_64-linux-gnu.so
mgo_processor/controllers/processor/ll_processor/order_processing.cpython-310-x86_64-linux-gnu.so
mgo_processor/controllers/processor/ll_processor/recovery.cpython-310-x86_64-linux-gnu.so
mgo_processor/controllers/processor/ll_processor/recurring_orders.cpython-310-x86_64-linux-gnu.so
mgo_prwrkpi-5.4.1.dist-info/METADATA
mgo_prwrkpi-5.4.1.dist-info/WHEEL
mgo_prwrkpi-5.4.1.dist-info/top_level.txt
mgo_prwrkpi-5.4.1.dist-info/RECORD
