Metadata-Version: 2.4
Name: mgo-prwrkpi
Version: 5.4.1
Author: Kelly Kapowski
Requires-Python: >=3.10
Requires-Dist: python-dotenv
Requires-Dist: pandas==1.5.3
Requires-Dist: numpy<=1.26.0
Requires-Dist: pdfrw==0.4
Requires-Dist: requests==2.25.1
Requires-Dist: tornado>=6.1
Requires-Dist: Cython
Requires-Dist: ftfy==5.8
Requires-Dist: urllib3==1.26.3
Requires-Dist: SQLAlchemy==1.*
Requires-Dist: filelock
Requires-Dist: psycopg2==2.8.5
Requires-Dist: python_crontab==2.5.1
Requires-Dist: websocket_client==0.57.0
Requires-Dist: psutil
Requires-Dist: sshtunnel
Requires-Dist: functions-framework
Requires-Dist: pycryptodome
Requires-Dist: keyrings.google.artifactregistry-auth
Requires-Dist: modelswrkpi
Requires-Dist: salutake
Requires-Dist: lime-orderswrkpi
Requires-Dist: alertswrkpi
Requires-Dist: google-cloud-pubsub
Requires-Dist: h2o==3.46.0.7
Requires-Dist: mgoaiwrkpi
